README.rst
setup.py
permutation_test/__init__.py
permutation_test/ap.py
permutation_test/csv_parser.py
permutation_test/functions.py
permutation_test/permtest.py
permutation_test.egg-info/PKG-INFO
permutation_test.egg-info/SOURCES.txt
permutation_test.egg-info/dependency_links.txt
permutation_test.egg-info/entry_points.txt
permutation_test.egg-info/not-zip-safe
permutation_test.egg-info/pbr.json
permutation_test.egg-info/requires.txt
permutation_test.egg-info/top_level.txt