Metadata-Version: 1.0
Name: permutation-test
Version: 0.14
Summary: Implementation of Fishers permutation test
Home-page: https://github.com/cmohl2013/permutation_test
Author: Christoph Moehl
Author-email: christoph.moehl@dzne.de
License: MIT
Platform: UNKNOWN
